Workbook

Sheet 投递策略
A1: 王似鹏｜2027秋招／实习可投岗位清单
A3: 筛选口径：2026-07-01至2026-08-30发布；届次包含2027届／应届／不限；本科可投；未按城市和企业性质限制。源表无截止时间，请投递前打开链接确认。
A5: =COUNTA(全部可投岗位!$D$5:$D$666) -> 662 | C5: =COUNTIF(全部可投岗位!$A$5:$A$666,"A 核心推荐") -> 557 | E5: =COUNTIF(全部可投岗位!$A$5:$A$666,"B 建议投递") -> 95 | G5: =COUNTIF(全部可投岗位!$A$5:$A$666,"C 可尝试") -> 10
A8: 全部可投 | C8: 核心推荐 | E8: 建议投递 | G8: 可尝试
A10: 岗位方向与投递策略
A11: 投递顺序 | B11: 岗位方向 | C11: 完整池数量 | D11: 建议简历 | E11: 定位与边界
A12: 1 | B12: Java后端 | C12: =COUNTIF(全部可投岗位!$B$5:$B$666,B12) -> 32 | D12: Java后端开发简历 | E12: Java政企项目、接口开发、SQL与性能优化直接匹配
A13: 2 | B13: AI应用开发 | C13: =COUNTIF(全部可投岗位!$B$5:$B$666,B13) -> 74 | D13: AI应用开发简历 | E13: 具备LLM、Prompt、结构化输出、接口与失败降级实践
A14: 3 | B14: 全栈开发 | C14: =COUNTIF(全部可投岗位!$B$5:$B$666,B14) -> 24 | D14: 全栈开发简历 | E14: 具备Spring Boot＋Vue及FastAPI＋React端到端实践
A15: 4 | B15: 通用软件开发 | C15: =COUNTIF(全部可投岗位!$B$5:$B$666,B15) -> 125 | D15: 通用软件开发简历 | E15: 具备后端、数据接口、联调、性能优化与部署验证经验
A16: 5 | B16: 通用FDE／实施交付 | C16: =COUNTIF(全部可投岗位!$B$5:$B$666,B16) -> 11 | D16: 通用FDE简历 | E16: 具备政企需求澄清、多方联调、数据接入及Docker部署验证经验
A17: 6 | B17: AI FDE／AI交付 | C17: =COUNTIF(全部可投岗位!$B$5:$B$666,B17) -> 7 | D17: AI FDE简历 | E17: 同时具备AI应用开发、客户协同与部署验证能力
A18: 7 | B18: 售前解决方案 | C18: =COUNTIF(全部可投岗位!$B$5:$B$666,B18) -> 38 | D18: 售前解决方案简历 | E18: 具备需求澄清、原型方案、演示答疑和技术可行性判断经验
A19: 8 | B19: 售后／技术支持 | C19: =COUNTIF(全部可投岗位!$B$5:$B$666,B19) -> 30 | D19: 售后／技术支持简历 | E19: 具备操作指导、问题闭环、日志核验和研发升级经验
A20: 9 | B20: 产品经理／产品助理 | C20: =COUNTIF(全部可投岗位!$B$5:$B$666,B20) -> 105 | D20: 产品经理／产品助理简历 | E20: 具备需求拆解、原型、功能规则、接口和研发联调经验
A21: 10 | B21: 项目经理／项目助理 | C21: =COUNTIF(全部可投岗位!$B$5:$B$666,B21) -> 33 | D21: 项目经理／项目助理简历 | E21: 具备22子系统、10家分包商和18个科室的交付协同经验
A22: 11 | B22: 大客户销售／ToB销售 | C22: =COUNTIF(全部可投岗位!$B$5:$B$666,B22) -> 86 | D22: 大客户销售简历 | E22: 具备真实陌拜成交经历及政企客户沟通经验
A23: 12 | B23: 商务拓展／BD | C23: =COUNTIF(全部可投岗位!$B$5:$B$666,B23) -> 12 | D23: ToB销售／商务拓展简历 | E23: 具备主动拓客、需求识别、方案表达与复购跟进经验
... A29: 18 | B29: 前端／全栈延伸 | C29: =COUNTIF(全部可投岗位!$B$5:$B$666,B29) -> 1 | D29: 全栈开发简历 | E29: 可尝试初级前端，复杂前端工程化仍需补强
A31: 暂不建议直接投递的岗位
A32: 岗位类型 | B32: 原因
A33: 大模型训练／算法研究 | B33: 当前优势在AI应用工程，不具备算法论文、训练或调优证据
A34: 渗透测试／安全攻防研发 | B34: 只有攻防演练协同经验，缺少独立攻防与安全工具实践
A35: 嵌入式／驱动／硬件研发 | B35: 现有技术栈以Java、Python、Web和数据平台为主
A36: 高级项目经理／独立项目负责人 | B36: 有交付协同经验，但尚未独立负责完整大型项目
A37: 机械设备维修类售后 | B37: 技术支持经历集中在软件系统、数据和接口场景

Sheet 优先投递
A1: 优先投递｜按方向选取近期高匹配岗位（每个方向最多20家公司）
A2: 建议先从本表开始投递；同一公司可对应多个方向。源表不包含截止日期，点击链接后需再次确认岗位开放状态与具体JD。
A4: 推荐等级 | B4: 目标方向 | C4: 公司名称 | D4: 推荐投递岗位 | E4: 企业性质 | F4: 行业分类 | G4: 工作地点 | H4: 届次 | I4: 学历要求 | J4: 更新时间 | K4: 匹配依据 | L4: 建议简历 | M4: 风险提醒 | N4: 公告链接 | O4: 投递链接 | P4: 投递状态 | Q4: 个人备注 | R4: 源表行号
A5: A 核心推荐 | B5: Java后端 | C5: 数马电子 | D5: Java后端开发工程师 | E5: 民企 | F5: 其他 | G5: 深圳 | H5: 2027届 | I5: 本科、硕士、博士 | J5: 46263 | K5: Java政企项目、接口开发、SQL与性能优化直接匹配 | L5: Java后端开发简历 | M5: 优先Java/Spring Boot岗位；明确要求其他主语言时谨慎 | N5: https://mp.weixin.qq.com/s/8zAcXxsG-ij5jiV90i3hJQ | O5: https://open.weixin.qq.com/connect/oauth2/authorize?appid=wxccc65987395c11e0&redirect_uri=https%3A%2F%2Fzhaopin.xhorse.net.cn%2Fbase%2Flogin%2Flogin%3Fr%3DaHR0cHM6Ly96aGFvcGluLnhob3JzZS5uZXQuY24vd2VjaGF0L3IyMDIyL2FwcGx5Mw%3D%3D&response_type=code&scope=snsapi_userinfo&state=STATE&connect_redirect=1#wechat_redirect | P5: 已投递 | R5: 24
A6: A 核心推荐 | B6: Java后端 | C6: 汉得信息 | D6: Java后端开发工程师 | E6: 民企 | F6: IT/互联网/游戏 | G6: 上海, 北京, 大连, 武汉, 广州, 全国多地 | H6: 2027届 | I6: 本科、硕士、博士 | J6: 46262 | K6: Java政企项目、接口开发、SQL与性能优化直接匹配 | L6: Java后端开发简历 | M6: 优先Java/Spring Boot岗位；明确要求其他主语言时谨慎 | N6: https://hand-china1.zhiye.com/campus/jobs | O6: https://hand-china1.zhiye.com/campus/jobs | P6: 未投递 | R6: 154
A7: A 核心推荐 | B7: Java后端 | C7: 奥克斯 | D7: JAVA 开发工程师 | E7: 民企 | F7: 耐用消费品 | G7: 全国多地, 宁波, 深圳, 上海, 鞍山, 芜湖 | H7: 2027届 | I7: 本科、硕士、博士 | J7: 46261 | K7: Java政企项目、接口开发、SQL与性能优化直接匹配 | L7: Java后端开发简历 | M7: 优先Java/Spring Boot岗位；明确要求其他主语言时谨慎 | N7: https://mp.weixin.qq.com/s/yJfCaHlrmrPpRCmnkgGYSQ | O7: https://auxgroup.zhiye.com/campus/jobs | P7: 已投递 | R7: 179
A8: A 核心推荐 | B8: Java后端 | C8: 大华股份 | D8: 大数据(Agent方向/Java方向/基础设施方向) | E8: 民企 | F8: 智能硬件, 通信/电子/半导体 | G8: 杭州, 全国多地, 海外 | H8: 2027届 | I8: 本科、硕士、博士 | J8: 46261 | K8: Java政企项目、接口开发、SQL与性能优化直接匹配 | L8: Java后端开发简历 | M8: 优先Java/Spring Boot岗位；明确要求其他主语言时谨慎 | N8: https://mp.weixin.qq.com/s/F1HrgjGfeTaf_OImQPR6BQ | O8: https://job.dahuatech.com/#/CampusPosition?id=11 | P8: 已投递 | Q8: 解决方案 | R8: 252
A9: A 核心推荐 | B9: Java后端 | C9: 禾赛科技 | D9: java 开发工程师 | E9: 民企 | F9: 智能硬件 | G9: 上海, 杭州 | H9: 2027届 | I9: 本科、硕士、博士 | J9: 46261 | K9: Java政企项目、接口开发、SQL与性能优化直接匹配 | L9: Java后端开发简历 | M9: 优先Java/Spring Boot岗位；明确要求其他主语言时谨慎 | N9: https://mp.weixin.qq.com/s/D880mQJRD_szYY2N4yyRaw | O9: https://kwh0jtf778.jobs.feishu.cn/229043/m/?spread=KHWW5AC | P9: 已投递 | R9: 178
A10: A 核心推荐 | B10: Java后端 | C10: 红茶移动 | D10: Java工程师 | E10: 民企 | F10: 通信/电子/半导体 | G10: 北京, 上海, 南昌, 武汉, 深圳, 珠海, 西安 | H10: 2027届 | I10: 本科、硕士 | J10: 46261 | K10: Java政企项目、接口开发、SQL与性能优化直接匹配 | L10: Java后端开发简历 | M10: 优先Java/Spring Boot岗位；明确要求其他主语言时谨慎 | N10: https://mp.weixin.qq.com/s/taEfcIXJ1NyiOSoJXW5xQg | O10: https://talentsphere.redteamobile.com/submit-resume | P10: 已投递 | Q10: java+全栈 | R10: 183
A11: A 核心推荐 | B11: Java后端 | C11: 中国电科32所 | D11: Java开发工程师 | E11: 央国企 | F11: IT/互联网/游戏, 教育/培训/科研 | G11: 北京, 上海, 南京, 武汉, 广州, 深圳, 成都 | H11: 2027届 | I11: 本科、硕士、博士 | J11: 46261 | K11: Java政企项目、接口开发、SQL与性能优化直接匹配 | L11: Java后端开发简历 | M11: 优先Java/Spring Boot岗位；明确要求其他主语言时谨慎 | N11: https://mp.weixin.qq.com/s/iiYejH9932MT8WKvMTj2Ig | O11: https://wecruit.hotjob.cn/SU66c447a01eb805432564cfaf/mc/position/campus | P11: 未投递 | R11: 181
A12: A 核心推荐 | B12: Java后端 | C12: 科大国创 | D12: Java开发工程师 | E12: 民企 | F12: IT/互联网/游戏 | G12: 合肥 | H12: 2027届 | I12: 本科、硕士、博士 | J12: 46260 | K12: Java政企项目、接口开发、SQL与性能优化直接匹配 | L12: Java后端开发简历 | M12: 优先Java/Spring Boot岗位；明确要求其他主语言时谨慎 | N12: https://gccloud.zhiye.com/campus/jobs?LocId=%5B%7B%22id%22%3A%223401%22%2C%22label%22%3A%22%E5%90%88%E8%82%A5%E5%B8%82%22%7D%5D | O12: https://gccloud.zhiye.com/campus/jobs?LocId=%5B%7B%22id%22%3A%223401%22%2C%22label%22%3A%22%E5%90%88%E8%82%A5%E5%B8%82%22%7D%5D | P12: 已投递 | R12: 388
A13: A 核心推荐 | B13: Java后端 | C13: 海能达 | D13: Java | E13: 民企 | F13: 通信/电子/半导体 | G13: 哈尔滨, 南京, 深圳, 东莞, 成都 | H13: 2027届 | I13: 本科、硕士、博士 | J13: 46259 | K13: Java政企项目、接口开发、SQL与性能优化直接匹配 | L13: Java后端开发简历 | M13: 优先Java/Spring Boot岗位；明确要求其他主语言时谨慎 | N13: https://mp.weixin.qq.com/s/1_h_CbdSgI97JAWdoA8HfQ | O13: https://app.mokahr.com/campus-recruitment/hytera/182194?locale=zh-CN#/jobs | P13: 已投递 | R13: 398
A14: A 核心推荐 | B14: Java后端 | C14: 研极微电 | D14: 流媒体/JAVA/大数据/Android/i0S | E14: 民企 | F14: 通信/电子/半导体, 机械/制造业 | G14: 深圳, 杭州, 北京, 苏州, 上海, 南京, 成都, 长沙, 西安, 天津 | H14: 2027届 | I14: 本科、硕士、博士 | J14: 46259 | K14: Java政企项目、接口开发、SQL与性能优化直接匹配 | L14: Java后端开发简历 | M14: 优先Java/Spring Boot岗位；明确要求其他主语言时谨慎 | N14: https://mp.weixin.qq.com/s/GtH8WNojHl9Fmq_UnqyRhQ | O14: https://mp.weixin.qq.com/s/GtH8WNojHl9Fmq_UnqyRhQ | P14: 未投递 | R14: 506
A15: A 核心推荐 | B15: Java后端 | C15: 中电信人工智能科技(北京)有限公司 | D15: Java开发工程师 | E15: 央国企 | F15: 通信/电子/半导体, IT/互联网/游戏 | G15: 北京, 成都, 西安 | H15: 2027届 | I15: 本科、硕士、博士 | J15: 46259 | K15: Java政企项目、接口开发、SQL与性能优化直接匹配 | L15: Java后端开发简历 | M15: 优先Java/Spring Boot岗位；明确要求其他主语言时谨慎 | N15: https://mp.weixin.qq.com/s/7-9-J5w7DtKhiZqzfOSC5Q | O15: https://wejob.chinatelecom.com.cn/wt/TELE/web/index | P15: 未投递 | R15: 458
A16: A 核心推荐 | B16: Java后端 | C16: 电科金仓 | D16: Java研发工程师 | E16: 央国企 | F16: IT/互联网/游戏 | G16: 北京, 天津, 上海, 青岛, 成都, 西安 | H16: 2027届 | I16: 本科、硕士、博士 | J16: 46258 | K16: Java政企项目、接口开发、SQL与性能优化直接匹配 | L16: Java后端开发简历 | M16: 优先Java/Spring Boot岗位；明确要求其他主语言时谨慎 | N16: https://mp.weixin.qq.com/s/BlYp6lXekH_Oo_kvRaAnYA | O16: https://app.mokahr.com/campus-recruitment/kingbase/47259?sourceToken=71b3c4ae3ab9e20a733ab2ffc8a556fe#/ | P16: 未投递 | R16: 551
A17: A 核心推荐 | B17: Java后端 | C17: 超星集团 | D17: Java开发工程师 | E17: 民企 | F17: IT/互联网/游戏, 教育/培训/科研 | G17: 北京, 廊坊, 上海, 南京, 福州, 郑州, 武汉, 成都, 西安, 全国多地 | H17: 2027届 | I17: 本科、硕士、博士 | J17: 46256 | K17: Java政企项目、接口开发、SQL与性能优化直接匹配 | L17: Java后端开发简历 | M17: 优先Java/Spring Boot岗位；明确要求其他主语言时谨慎 | N17: https://mp.weixin.qq.com/s/wbqLJ4BO6d2fMwRId73cyw | O17: https://office.chaoxing.com/apps/forms/web/apply.html?mappId=20830777&openid=&id=3506323&enc=e33beb1ece876d01195257eaf2b4411e&formAppId=&fidEnc=e1415bf352644bc0&userLoginInfo=userInfodeptId329906id6460563inserttime1618813515000mobileuid173679788unameupdatetime1726649085000&defaultUid=173679788&uuid=db8b5c33c8c3447dba081db3321a4e49&checkCode=b837e5617e6b4f7c82a1eb67215ebe80 | P17: 未投递 | R17: 651
A18: A 核心推荐 | B18: Java后端 | C18: 华诺星空 | D18: JAVA开发工程师 | E18: 民企 | F18: 通信/电子/半导体, 机械/制造业 | G18: 北京, 杭州, 济南, 长沙, 深圳, 成都, 西安, 海外 | H18: 2027届 | I18: 本科、硕士、博士 | J18: 46256 | K18: Java政企项目、接口开发、SQL与性能优化直接匹配 | L18: Java后端开发简历 | M18: 优先Java/Spring Boot岗位；明确要求其他主语言时谨慎 | N18: https://mp.weixin.qq.com/s/oeQ-u9zgnhog4ipz5bkblg | O18: https://app.mokahr.com/m/campus-recruitment/novasky/146544?locale=zh-CN | P18: 未投递 | R18: 660
A19: A 核心推荐 | B19: Java后端 | C19: ZBS POS | D19: Java开发工程师 | E19: 民企 | F19: IT/互联网/游戏 | G19: 福州, 海外 | H19: 2026届, 2027届 | I19: 本科、硕士、博士 | J19: 46256 | K19: Java政企项目、接口开发、SQL与性能优化直接匹配 | L19: Java后端开发简历 | M19: 优先Java/Spring Boot岗位；明确要求其他主语言时谨慎 | N19: https://mp.weixin.qq.com/s/IRefPcgjJ35-lBGrkyJLZg | O19: https://s.xinrenxinshi.com/recruitGate/home#/ey=0ebdb0048e4472688f15cda6cc39564385c764 | P19: 未投递 | R19: 633
A20: A 核心推荐 | B20: Java后端 | C20: 数码视讯 | D20: Java开发工程师 | E20: 民企 | F20: 通信/电子/半导体, IT/互联网/游戏 | G20: 北京, 西安, 全国多地 | H20: 2027届 | I20: 本科、硕士、博士 | J20: 46255 | K20: Java政企项目、接口开发、SQL与性能优化直接匹配 | L20: Java后端开发简历 | M20: 优先Java/Spring Boot岗位；明确要求其他主语言时谨慎 | N20: https://mp.weixin.qq.com/s/Rrc6FVQO-MFrPMXggAcWiw | O20: https://doc.weixin.qq.com/forms/AO8A7AfQAAwAasAkAYXAHUCNcNvtiBdQf?sid=zw45TIxccW4uDGNvAOxURQAA#/blankpage?type=blank | P20: 未投递 | R20: 720
A21: A 核心推荐 | B21: Java后端 | C21: 迈睿机器人 | D21: Java开发工程师 | E21: 民企 | F21: 智能硬件 | G21: 杭州 | H21: 2027届 | I21: 本科、硕士、博士 | J21: 46254 | K21: Java政企项目、接口开发、SQL与性能优化直接匹配 | L21: Java后端开发简历 | M21: 优先Java/Spring Boot岗位；明确要求其他主语言时谨慎 | N21: https://mp.weixin.qq.com/s/z-D6D7586U5COVF3AECdvw | O21: https://www.zhipin.com/gongsi/job/23220e01d12955bc1X143926EQ~~.html?ka=company-jobs | P21: 未投递 | R21: 741
A22: A 核心推荐 | B22: Java后端 | C22: 优必选科技 | D22: Java开发工程师 | E22: 民企 | F22: 智能硬件 | G22: 深圳, 柳州 | H22: 2027届, 2026届 | I22: 本科、硕士、博士 | J22: 46254 | K22: Java政企项目、接口开发、SQL与性能优化直接匹配 | L22: Java后端开发简历 | M22: 优先Java/Spring Boot岗位；明确要求其他主语言时谨慎 | N22: https://mp.weixin.qq.com/s/B7ozYeztCo5hmM4mU2mIng | O22: https://ubtrobot.zhiye.com/campus/jobs | P22: 未投递 | R22: 742
... A230: A 核心推荐 | B230: 商务拓展／BD | C230: 施耐德电气-新星计划 | D230: 业务拓展 | E230: 外企 | F230: 机械/制造业 | G230: 北京, 张家口, 呼和浩特, 上海, 无锡, 厦门, 济南, 青岛, 武汉, 广州, 珠海, 西安 | H230: 2027届 | I230: 本科、硕士、博士 | J230: 46248 | K230: 具备主动拓客、需求识别、方案表达与复购跟进经验 | L230: ToB销售／商务拓展简历 | M230: 优先ToB及技术产品场景 | N230: https://mp.weixin.qq.com/s/8nrFaxSzK0NrX8MKLVmQkA | O230: https://www.zhipin.com/zt/schneider/xingyipeixunsheng.html | P230: 未投递 | R230: 1120

Sheet 全部可投岗位
A1: 全部可投岗位｜基于现有简历方向的完整筛选池
A2: A＝与现有简历直接匹配；B＝相邻方向，建议核对JD后投递；C＝可以尝试但需补能力。未按地点和企业性质过滤。
A4: 推荐等级 | B4: 主要方向 | C4: 其他匹配方向 | D4: 公司名称 | E4: 推荐投递岗位 | F4: 企业性质 | G4: 行业分类 | H4: 工作地点 | I4: 届次 | J4: 学历要求 | K4: 更新时间 | L4: 匹配依据 | M4: 建议简历 | N4: 风险提醒 | O4: 公告链接 | P4: 投递链接 | Q4: 投递状态 | R4: 个人备注 | S4: 源表行号
A5: A 核心推荐 | B5: AI FDE／AI交付 | C5: Java后端；AI应用开发；软件测试／测试开发；售后／技术支持；另有4项 | D5: 大华股份 | E5: 大数据(Agent方向/Java方向/基础设施方向)；AI应用开发；软件测试；测试开发(AI应用测试方向)；技术支持；AI交付；另有5个匹配岗位（详见公告） | F5: 民企 | G5: 智能硬件, 通信/电子/半导体 | H5: 杭州, 全国多地, 海外 | I5: 2027届 | J5: 本科、硕士、博士 | K5: 46261 | L5: Java政企项目、接口与SQL优化经验直接匹配；具备LLM、Prompt、结构化输出和失败降级实践；另有1项 | M5: Java后端开发简历；AI应用开发简历；通用软件开发简历（需补测试表述）；另有1项 | N5: 可投，但需补充测试用例、接口测试或自动化测试证据；适合作为拓展方向，优先ToB、技术或行业客户场景；另有2项 | O5: https://mp.weixin.qq.com/s/F1HrgjGfeTaf_OImQPR6BQ | P5: https://job.dahuatech.com/#/CampusPosition?id=11 | Q5: 未投递 | S5: 252
A6: A 核心推荐 | B6: AI FDE／AI交付 | C6: 产品经理／产品助理；AI FDE／AI交付；营销管培／市场销售；后端开发延伸；另有5项 | D6: 海尔 | E6: AI‑数据产品经理；AI 产品经理；工业 AI 平台产品经理；FDE 工程师（AI 前线部署工程师）；国内销售管理；IT 产品经理；另有20个匹配岗位（详见公告） | F6: 民企 | G6: 耐用消费品, 智能硬件 | H6: 北京, 天津, 沈阳, 大连, 上海, 苏州, 杭州, 合肥, 青岛, 烟台, 郑州, 武汉, 广州, 深圳, 佛山, 重庆, 遵义, 西安, 全国多地, 海外 | I6: 2027届 | J6: 本科、硕士、博士 | K6: 46261 | L6: 具备需求拆解、原型、功能规则和研发联调经验；同时具备AI应用开发、客户协同和部署验证能力；另有1项 | M6: 产品经理／产品助理简历；AI FDE简历；大客户销售／ToB销售简历；另有1项 | N6: 优先产品助理、校招产品经理；避免要求成熟商业化经验的岗位；另有6项 | O6: https://mp.weixin.qq.com/s/Yf8ixFofh_44r7_7k1BEdA | P6: https://maker.haier.net/client/campus/activityindex.html | Q6: 未投递 | S6: 180
A7: A 核心推荐 | B7: AI FDE／AI交付 | C7: 大客户销售／ToB销售；AI FDE／AI交付 | D7: 百度智能云 | E7: 云和大模型大客户销售；云和大模型售前解决方案工程师 | F7: 民企 | G7: IT/互联网/游戏 | H7: 北京, 上海, 苏州, 南京, 深圳, 郑州, 杭州 | I7: 2027届 | J7: 本科、硕士、博士 | K7: 46256 | L7: 具备真实陌拜成交经历及政企客户沟通经验；同时具备AI应用开发、客户协同和部署验证能力 | M7: 大客户销售简历；AI FDE简历 | N7: 与现有简历方向直接匹配，投递前仍需核对具体JD与专业限制 | O7: https://mp.weixin.qq.com/s/-5DXqaanhqP2fuq19v3Usg?scene=1&click_id=597600455 | P7: https://talent.baidu.com/jobs/list | Q7: 未投递 | S7: 677
A8: A 核心推荐 | B8: AI FDE／AI交付 | C8: 后端开发延伸；软件测试／测试开发；数据平台／数据开发；AI FDE／AI交付；另有1项 | D8: 星环科技 | E8: 后端开发工程师；AI测试开发工程师；数据开发工程师；AI交付工程师；售前工程师 | F8: 民企 | G8: IT/互联网/游戏 | H8: 上海, 北京, 南京, 广州, 成都 | I8: 2027届 | J8: 本科、硕士、博士 | K8: 46252 | L8: 具备Java后端基础，可尝试未限定语言的初级后端岗位；具备接口联调、问题跟踪和部署验证经验，但测试专项较弱；另有1项 | M8: Java后端／通用软件开发简历；通用软件开发简历（需补测试表述）；AI FDE简历；另有1项 | N8: 投递前确认技术栈以Java为主；明确要求其他语言的不建议投；另有3项 | O8: https://mp.weixin.qq.com/s/liA3cgqxMjrBr4Sb2lv8sA | P8: https://app.mokahr.com/campus_apply/transwarp/3196#/jobs | Q8: 未投递 | S8: 902
A9: A 核心推荐 | B9: AI FDE／AI交付 | C9: AI FDE／AI交付；大客户销售／ToB销售 | D9: 瑞浦兰钧能源 | E9: AI解决方案工程师；销售工程师 | F9: 民企 | G9: 新能源 | H9: 温州, 佛山, 柳州, 重庆, 海外, 嘉兴 | I9: 2027届 | J9: 本科、硕士、博士 | K9: 46246 | L9: 同时具备AI应用开发、客户协同和部署验证能力；具备真实陌拜成交经历及政企客户沟通经验 | M9: AI FDE简历；大客户销售简历 | N9: 与现有简历方向直接匹配，投递前仍需核对具体JD与专业限制 | O9: https://mp.weixin.qq.com/s/moQEzqfXLldRZU1dp8zCAw | P9: https://app.mokahr.com/campus-recruitment/chinarept/166544?locale=zh-CN#/jobs | Q9: 未投递 | S9: 1171
A10: A 核心推荐 | B10: AI FDE／AI交付 | C10: AI FDE／AI交付 | D10: 合合信息 | E10: 大模型算法工程师 数据分析师测试工程师运营经理 客户成功 产运管培生AI全栈开发工程师用户研究产品经理AI创新设计师AI数据分析师AI产品经理移动端开发工程师FDE工程师AI软件… | F10: 民企 | G10: IT/互联网/游戏 | H10: 上海 | I10: 2027届 | J10: 本科、硕士、博士 | K10: 46231 | L10: 同时具备AI应用开发、客户协同和部署验证能力 | M10: AI FDE简历 | N10: 与现有简历方向直接匹配，投递前仍需核对具体JD与专业限制 | O10: https://mp.weixin.qq.com/s/2_pB0aazu6eVZnjsrWyCzA | P10: https://intsig.zhiye.com/campus/jobs?sessionid=733543115 | Q10: 未投递 | S10: 1654
A11: A 核心推荐 | B11: AI FDE／AI交付 | C11: AI FDE／AI交付 | D11: 施耐德电气 | E11: AI工具开发 intern AI咨询实习生 数字化创新实习生 AI-PMO项目实习生 AI数据模型开发实习生 AI开发实习生 AI产品实习生 AI解决方案设计实习生 | F11: 外企 | G11: 机械/制造业 | H11: 上海, 北京, 广州 | I11: 2027届 | J11: 本科,硕士,博士 | K11: 46223 | L11: 同时具备AI应用开发、客户协同和部署验证能力 | M11: AI FDE简历 | N11: 与现有简历方向直接匹配，投递前仍需核对具体JD与专业限制 | O11: https://mp.weixin.qq.com/s/saBUKqMXeJFcynrlL2BcYA?scene=25&id=spzT3M&Esessionid=&click_id=3#wechat_redirect | P11: https://www.zhipin.com/zt/schneider/ai_star_shixisheng.html | Q11: 未投递 | S11: 1838
A12: A 核心推荐 | B12: Java后端 | C12: Java后端；通用软件开发；营销管培／市场销售 | D12: 数马电子 | E12: Java后端开发工程师；CAM软件开发工程师；海外销售；国内销售 | F12: 民企 | G12: 其他 | H12: 深圳 | I12: 2027届 | J12: 本科、硕士、博士 | K12: 46263 | L12: Java政企项目、接口与SQL优化经验直接匹配；具备软件工程基础、后端开发、联调和部署验证经验；另有1项 | M12: Java后端开发简历；通用软件开发简历；大客户销售／ToB销售简历 | N12: 适合作为拓展方向，优先ToB、技术或行业客户场景 | O12: https://mp.weixin.qq.com/s/8zAcXxsG-ij5jiV90i3hJQ | P12: https://open.weixin.qq.com/connect/oauth2/authorize?appid=wxccc65987395c11e0&redirect_uri=https%3A%2F%2Fzhaopin.xhorse.net.cn%2Fbase%2Flogin%2Flogin%3Fr%3DaHR0cHM6Ly96aGFvcGluLnhob3JzZS5uZXQuY24vd2VjaGF0L3IyMDIyL2FwcGx5Mw%3D%3D&response_type=code&scope=snsapi_userinfo&state=STATE&connect_redirect=1#wechat_redirect | Q12: 未投递 | S12: 24
A13: A 核心推荐 | B13: AI应用开发 | C13: AI应用开发；通用软件开发 | D13: 华为-云核心网产品线 | E13: AI应用工程师；软件开发工程师 | F13: 民企 | G13: IT/互联网/游戏 | H13: 上海, 西安, 北京, 东莞, 杭州, 南京 | I13: 2027届 | J13: 本科、硕士、博士 | K13: 46262 | L13: 具备LLM、Prompt、结构化输出和失败降级实践；具备软件工程基础、后端开发、联调和部署验证经验 | M13: AI应用开发简历；通用软件开发简历 | N13: 与现有简历方向直接匹配，投递前仍需核对具体JD与专业限制 | O13: https://mp.weixin.qq.com/s/Kf2yi_fiBx0Ystenq754gw | P13: https://docs.qq.com/form/page/DWkJPWWpBSFVMdkJ6#/fill | Q13: 未投递 | S13: 145
A14: A 核心推荐 | B14: AI应用开发 | C14: 大客户销售／ToB销售；AI应用开发；项目经理／项目助理；产品经理／产品助理 | D14: 坤维科技 | E14: 技术销售工程师；Ai应用工程师；项目经理；产品经理 | F14: 民企 | G14: 通信/电子/半导体, 机械/制造业 | H14: 北京, 上海, 常州, 深圳 | I14: 2026届, 2027届 | J14: 本科、硕士、博士 | K14: 46262 | L14: 具备真实陌拜成交经历及政企客户沟通经验；具备LLM、Prompt、结构化输出和失败降级实践；另有1项 | M14: 大客户销售简历；AI应用开发简历；项目经理／项目助理简历；另有1项 | N14: 优先项目助理、交付、PMO及培养岗；避免要求独立负责大型项目；另有2项 | O14: https://mp.weixin.qq.com/s/vKdCaI10x9ayhryoeLGP6A | P14: https://mp.weixin.qq.com/s/vKdCaI10x9ayhryoeLGP6A | Q14: 未投递 | S14: 106
A15: A 核心推荐 | B15: Java后端 | C15: Java后端 | D15: 汉得信息 | E15: 数智化咨询顾问Java后端开发工程师全栈开发工程师 数据开发工程师Java后端研发工程师 产品经理数智化规划咨询顾问 | F15: 民企 | G15: IT/互联网/游戏 | H15: 上海, 北京, 大连, 武汉, 广州, 全国多地 | I15: 2027届 | J15: 本科、硕士、博士 | K15: 46262 | L15: Java政企项目、接口与SQL优化经验直接匹配 | M15: Java后端开发简历 | N15: 与现有简历方向直接匹配，投递前仍需核对具体JD与专业限制 | O15: https://hand-china1.zhiye.com/campus/jobs | P15: https://hand-china1.zhiye.com/campus/jobs | Q15: 未投递 | S15: 154
A16: A 核心推荐 | B16: AI应用开发 | C16: 软件测试／测试开发；售后／技术支持；大客户销售／ToB销售；AI应用开发 | D16: 紫光同芯 | E16: 软件测试；技术支持；客户经理；AI应用工程师 | F16: 央国企 | G16: IT/互联网/游戏 | H16: 北京, 上海, 无锡, 武汉, 成都, 西安 | I16: 2027届 | J16: 本科、硕士、博士 | K16: 46262 | L16: 具备接口联调、问题跟踪和部署验证经验，但测试专项较弱；具备操作指导、问题闭环、日志核验和研发升级经验；另有1项 | M16: 通用软件开发简历（需补测试表述）；售后／技术支持简历；大客户销售简历；另有1项 | N16: 可投，但需补充测试用例、接口测试或自动化测试证据 | O16: https://mp.weixin.qq.com/s/cPtCk8n1Dx2EP9khi-XESQ | P16: https://app.mokahr.com/campus-recruitment/tsinghuaic/39656#/jobs | Q16: 未投递 | S16: 134
... A333: A 核心推荐 | B333: 产品经理／产品助理 | C333: 产品经理／产品助理；数据平台／数据开发 | D333: 阿里健康 | E333: AI产品经理；AI数据工程师 | F333: 民企 | G333: 医疗/医药/生物 | H333: 杭州 | I333: 2027届 | J333: 本科、硕士、博士 | K333: 46240 | L333: 具备需求拆解、原型、功能规则和研发联调经验；具备多数据源接入、SQL、聚合接口和库表设计经验 | M333: 产品经理／产品助理简历；Java后端／通用软件开发简历 | N333: 优先产品助理、校招产品经理；避免要求成熟商业化经验的岗位；另有2项 | O333: https://mp.weixin.qq.com/s/ATedCla5Btu-Cus8_wd7Kw | P333: https://campus-talent.alibaba.com/campus/index | Q333: 未投递 | S333: 1375
A334: A 核心推荐 | B334: 产品经理／产品助理 | C334: 产品经理／产品助理 | D334: Shopee | E334: 产品经理培训生 | G334: 贸易/批发/零售 | H334: 北京 | I334: 2025届, 2026届, 2027届 | J334: 本科、硕士、博士 | K334: 46239 | L334: 具备需求拆解、原型、功能规则和研发联调经验 | M334: 产品经理／产品助理简历 | N334: 优先产品助理、校招产品经理；避免要求成熟商业化经验的岗位 | O334: https://mp.weixin.qq.com/s/S0Y1o9krN1pmUnGReK0NHA | P334: https://mp.weixin.qq.com/s/S0Y1o9krN1pmUnGReK0NHA | Q334: 未投递 | S334: 1395
A335: A 核心推荐 | B335: 大客户销售／ToB销售 | C335: 大客户销售／ToB销售 | D335: 加多宝集团 | E335: 销售管培生 | F335: 民企 | G335: 快速消费品 | H335: 北京, 石家庄, 杭州, 温州, 合肥, 石狮, 南昌, 赣州, 郑州, 漯河, 武汉, 广州, 深圳, 清远, 东莞, 成都, 绵阳, 资阳, 毕节, 昆明, 玉溪, 西安, 兰州, 格尔木 | I335: 2027届 | J335: 本科、硕士、博士 | K335: 46238 | L335: 具备真实陌拜成交经历及政企客户沟通经验 | M335: 大客户销售简历 | N335: 与现有简历方向直接匹配，投递前仍需核对具体JD与专业限制 | O335: https://mp.weixin.qq.com/s/iVg7rGYfBreVZOitM6r42Q | P335: https://jdbchina.zhiye.com/ | Q335: 未投递 | S335: 1420
A336: A 核心推荐 | B336: 大客户销售／ToB销售 | C336: 大客户销售／ToB销售；商务拓展／BD | D336: 华为ICT销售 | E336: 客户经理；合同商务经理 | F336: 民企 | G336: IT/互联网/游戏 | H336: 全国多地 | I336: 2027届 | J336: 本科、硕士、博士 | K336: 46238 | L336: 具备真实陌拜成交经历及政企客户沟通经验；具备主动拓客、需求识别、方案表达和复购跟进经验 | M336: 大客户销售简历；ToB销售／商务拓展简历 | N336: 与现有简历方向直接匹配，投递前仍需核对具体JD与专业限制 | O336: https://mp.weixin.qq.com/s/hOfmHV5w4hT3LLX7SIKLOg?scene=1&click_id=73941632 | P336: https://mp.weixin.qq.com/s/hOfmHV5w4hT3LLX7SIKLOg?scene=1&click_id=73941632 | Q336: 未投递 | S336: 1434
A337: A 核心推荐 | B337: 产品经理／产品助理 | C337: 产品经理／产品助理 | D337: 哔哩哔哩 | E337: 产品运营 | F337: 民企 | G337: IT/互联网/游戏 | H337: 北京, 上海, 深圳, 海外 | I337: 2027届 | J337: 本科、硕士、博士 | K337: 46238 | L337: 具备需求拆解、原型、功能规则和研发联调经验 | M337: 产品经理／产品助理简历 | N337: 优先产品助理、校招产品经理；避免要求成熟商业化经验的岗位 | O337: https://mp.weixin.qq.com/s/L8XPLx10ozpCu_AUVx-RnQ | P337: https://jobs.bilibili.com/campus/positions?type=3 | Q337: 未投递 | S337: 1423
A338: A 核心推荐 | B338: 大客户销售／ToB销售 | C338: 大客户销售／ToB销售 | D338: 恪赛科技 | E338: 系统工程师 天线工程师射频工程师 通信工程师结构工程师 FPGA工程师 算法工程师嵌入式工程师 测试工程师 销售工程师 质量工程师采购工程师 财务专员人力专员项目管理专员 | F338: 民企 | G338: 通信/电子/半导体 | H338: 成都 | I338: 2027届 | J338: 本科、硕士 | K338: 46238 | L338: 具备真实陌拜成交经历及政企客户沟通经验 | M338: 大客户销售简历 | N338: 与现有简历方向直接匹配，投递前仍需核对具体JD与专业限制 | O338: https://mp.weixin.qq.com/s/VKhZxhYyd5-rJImEpQW0Yg | P338: https://mp.weixin.qq.com/s/VKhZxhYyd5-rJImEpQW0Yg | Q338: 未投递 | S338: 1415
A339: A 核心推荐 | B339: 产品经理／产品助理 | C339: 产品经理／产品助理 | D339: 赛乐医疗 | E339: 国內销售工程师 助理电子工程师影像算法工程师产品专员 赋能中心管培生国际市场专员海外销售工程师助理机械工程师 | F339: 民企 | G339: 医疗/医药/生物 | H339: 常州 | I339: 2027届 | J339: 本科、硕士、博士 | K339: 46238 | L339: 具备需求拆解、原型、功能规则和研发联调经验 | M339: 产品经理／产品助理简历 | N339: 优先产品助理、校招产品经理；避免要求成熟商业化经验的岗位 | O339: https://sifary.zhiye.com/campus/jobs | P339: https://sifary.zhiye.com/campus/jobs | Q339: 未投递 | S339: 1414
A340: A 核心推荐 | B340: 产品经理／产品助理 | C340: 产品经理／产品助理 | D340: FESCO星球 | E340: 产品运营实习生 | F340: 民企 | G340: IT/互联网/游戏 | H340: 北京 | I340: 2027届, 2028届 | J340: 本科、硕士、博士 | K340: 46237 | L340: 具备需求拆解、原型、功能规则和研发联调经验 | M340: 产品经理／产品助理简历 | N340: 优先产品助理、校招产品经理；避免要求成熟商业化经验的岗位 | O340: https://mp.weixin.qq.com/s/5SJpqcFDHTMaerdp4lgMLA | P340: https://mp.weixin.qq.com/s/5SJpqcFDHTMaerdp4lgMLA | Q340: 未投递 | S340: 1492
A341: A 核心推荐 | B341: 产品经理／产品助理 | C341: 产品经理／产品助理 | D341: 元气森林 | E341: 饮料产品经理品牌经理数字营销设计类 | F341: 民企 | G341: 快速消费品 | H341: 北京, 上海 | I341: 2027届 | J341: 本科、硕士、博士 | K341: 46237 | L341: 具备需求拆解、原型、功能规则和研发联调经验 | M341: 产品经理／产品助理简历 | N341: 优先产品助理、校招产品经理；避免要求成熟商业化经验的岗位 | O341: https://mp.weixin.qq.com/s/tpcmkw53mFzE4GiIwCogTw | P341: https://k11pnjpvz1.jobs.feishu.cn/352020/?sessionid= | Q341: 未投递 | S341: 1460
A342: A 核心推荐 | B342: 产品经理／产品助理 | C342: 产品经理／产品助理；大客户销售／ToB销售；营销管培／市场销售 | D342: 海信集团 | E342: 信动力M计划-海外产品经理；信动力M计划-海外销售经理；信动力M计划-营销管理类 | F342: 央国企 | G342: 耐用消费品 | H342: 青岛, 深圳, 武汉, 上海, 杭州, 西安, 贵阳, 江门, 扬州, 成都, 湖州, 佛山 | I342: 2026届, 2027届 | J342: 本科、硕士、博士 | K342: 46237 | L342: 具备需求拆解、原型、功能规则和研发联调经验；具备真实陌拜成交经历及政企客户沟通经验；另有1项 | M342: 产品经理／产品助理简历；大客户销售简历；大客户销售／ToB销售简历 | N342: 优先产品助理、校招产品经理；避免要求成熟商业化经验的岗位；另有1项 | O342: https://mp.weixin.qq.com/s/OP4JwYsQwnDUKNG6AzKIiw | P342: https://jobs.hisense.com/7/jobs | Q342: 未投递 | S342: 1471
A343: A 核心推荐 | B343: 产品经理／产品助理 | C343: 产品经理／产品助理；前端／全栈延伸 | D343: 盛趣游戏 | E343: AI产品运营实习生；web前端开发实习生 | F343: 民企 | G343: IT/互联网/游戏 | H343: 上海 | I343: 2027届, 2028届 | J343: 本科、硕士、博士 | K343: 46237 | L343: 具备需求拆解、原型、功能规则和研发联调经验；具备Vue、React管理台及前后端联调经验 | M343: 产品经理／产品助理简历；全栈开发简历 | N343: 优先产品助理、校招产品经理；避免要求成熟商业化经验的岗位；另有2项 | O343: https://mp.weixin.qq.com/s/KBNXJ0uy3wq5bOJsC2_sew | P343: https://mp.weixin.qq.com/s/KBNXJ0uy3wq5bOJsC2_sew | Q343: 未投递 | S343: 1482
A344: A 核心推荐 | B344: 产品经理／产品助理 | C344: 数据平台／数据开发；产品经理／产品助理；商务拓展／BD | D344: 量潮科技 | E344: 数据工程师；产品经理；商务经理 | F344: 民企 | G344: IT/互联网/游戏 | H344: 厦门 | I344: 2027届, 2028届 | J344: 本科、硕士、博士 | K344: 46237 | L344: 具备多数据源接入、SQL、聚合接口和库表设计经验；具备需求拆解、原型、功能规则和研发联调经验；另有1项 | M344: Java后端／通用软件开发简历；产品经理／产品助理简历；ToB销售／商务拓展简历 | N344: 适合数据接口/数据平台；不投算法型数据科学岗位；另有2项 | O344: https://mp.weixin.qq.com/s/MHbL-JiqOQB3oTuORGWPzw | P344: https://mp.weixin.qq.com/s/MHbL-JiqOQB3oTuORGWPzw | Q344: 未投递 | S344: 1491
A345: A 核心推荐 | B345: 产品经理／产品助理 | C345: 产品经理／产品助理 | D345: 引力波智谱 | E345: 研发产品运营市场设计 | F345: 民企 | G345: 机械/制造业 | H345: 合肥 | I345: 2027届 | J345: 本科、硕士、博士 | K345: 46236 | L345: 具备需求拆解、原型、功能规则和研发联调经验 | M345: 产品经理／产品助理简历 | N345: 优先产品助理、校招产品经理；避免要求成熟商业化经验的岗位 | O345: https://mp.weixin.qq.com/s/wShDj1JRbewUWau-BDxtdw?scene=1&click_id=838735726 | P345: https://gamstek.com/campus-recruitment/jobs/ | Q345: 未投递 | S345: 1513
A346: A 核心推荐 | B346: 大客户销售／ToB销售 | C346: 大客户销售／ToB销售 | D346: 微风安全 | E346: 销售代表 | F346: 民企 | G346: IT/互联网/游戏 | H346: 北京, 上海, 广州, 江苏, 浙江, 湖北 | I346: 2027届 | J346: 本科、硕士、博士 | K346: 46235 | L346: 具备真实陌拜成交经历及政企客户沟通经验 | M346: 大客户销售简历 | N346: 与现有简历方向直接匹配，投递前仍需核对具体JD与专业限制 | O346: https://mp.weixin.qq.com/s/hABxfwraM9VEIepi2KI1bA | P346: https://mp.weixin.qq.com/s/hABxfwraM9VEIepi2KI1bA | Q346: 未投递 | S346: 1533
... A378: A 核心推荐 | B378: 大客户销售／ToB销售 | C378: 大客户销售／ToB销售 | D378: 中原普惠担保 | E378: 客户经理助理实习生 | F378: 央国企 | G378: 金融业 | H378: 鹤壁 | I378: 2027届 | J378: 本科,硕士,博士 | K378: 46204 | L378: 具备真实陌拜成交经历及政企客户沟通经验 | M378: 大客户销售简历 | N378: 与现有简历方向直接匹配，投递前仍需核对具体JD与专业限制 | O378: https://mp.weixin.qq.com/s/7mPuik57vV8hd_trYTHDDg?click_id=611587066 | P378: https://mp.weixin.qq.com/s/7mPuik57vV8hd_trYTHDDg?click_id=611587066 | Q378: 未投递 | S378: 2111
A379: A 核心推荐 | B379: 大客户销售／ToB销售 | C379: 大客户销售／ToB销售 | D379: 思瑞浦 | E379: 技术销售管培生 | G379: 通信/电子/半导体 | H379: 上海, 北京, 天津, 成都, 杭州, 深圳, 苏州, 西安, 海外 | I379: 2027届 | J379: 本科,硕士,博士 | K379: 46204 | L379: 具备真实陌拜成交经历及政企客户沟通经验 | M379: 大客户销售简历 | N379: 与现有简历方向直接匹配，投递前仍需核对具体JD与专业限制 | O379: https://mp.weixin.qq.com/s/rX79HCOMQixzkw3ZkVvy0w | P379: https://app.mokahr.com/campus-recruitment/3peakic/67894?locale=zh-CN#/ | Q379: 未投递 | S379: 2110
A380: A 核心推荐 | B380: 产品经理／产品助理 | C380: 产品经理／产品助理 | D380: 艾达乐博 | E380: 平台产品经理 | F380: 民企 | G380: IT/互联网/游戏 | H380: 北京, 成都 | I380: 2027届 | J380: 本科,硕士,博士 | K380: 46204 | L380: 具备需求拆解、原型、功能规则和研发联调经验 | M380: 产品经理／产品助理简历 | N380: 优先产品助理、校招产品经理；避免要求成熟商业化经验的岗位 | O380: https://mp.weixin.qq.com/s/i6VdPEBxVxYP20DZSjcvcQ | P380: https://idealabs.world/ | Q380: 未投递 | S380: 2112
A381: A 核心推荐 | B381: 大客户销售／ToB销售 | C381: 大客户销售／ToB销售 | D381: 金华成泰农商银行 | E381: 客户经理实习助理 | G381: 金融业 | H381: 金华 | I381: 2027届 | J381: 本科,硕士,博士 | K381: 46204 | L381: 具备真实陌拜成交经历及政企客户沟通经验 | M381: 大客户销售简历 | N381: 与现有简历方向直接匹配，投递前仍需核对具体JD与专业限制 | O381: https://mp.weixin.qq.com/s/wyrYLW-IKhLh-BGxWDJBFg | P381: https://mp.weixin.qq.com/s/wyrYLW-IKhLh-BGxWDJBFg | Q381: 未投递 | S381: 2117
A382: A 核心推荐 | B382: 通用软件开发 | C382: 通用软件开发；数字化／IT项目 | D382: Molex莫仕 | E382: 软件开发工程师；软件助理工程师；数字化工程师 | F382: 外企 | G382: 通信/电子/半导体 | H382: 珠海 | I382: 2027届 | J382: 本科、硕士、博士 | K382: 46263 | L382: 具备软件工程基础、后端开发、联调和部署验证经验；具备政企信息化、多源数据和交付协同背景 | M382: 通用软件开发简历；项目交付／通用软件开发简历 | N382: 与现有简历方向直接匹配，投递前仍需核对具体JD与专业限制 | O382: https://mp.weixin.qq.com/s/Yo_GCQ0Q6gpLhhDGEaRreg | P382: https://campus.51job.com/koch2026/job.html | Q382: 未投递 | S382: 8
A383: A 核心推荐 | B383: 通用软件开发 | C383: 通用软件开发；售后／技术支持 | D383: 中电海康 | E383: 软件研发类；营销/技术支持类 | F383: 央国企 | G383: 通信/电子/半导体 | H383: 杭州 | I383: 2027届 | J383: 本科、硕士、博士 | K383: 46263 | L383: 具备软件工程基础、后端开发、联调和部署验证经验；具备操作指导、问题闭环、日志核验和研发升级经验 | M383: 通用软件开发简历；售后／技术支持简历 | N383: 与现有简历方向直接匹配，投递前仍需核对具体JD与专业限制 | O383: https://mp.weixin.qq.com/s/qtA7eWQpz6XNnKYuEiNfBg | P383: https://wecruit.hotjob.cn/SU630076febef57c3179e31260/pb/school.html | Q383: 未投递 | S383: 3
A384: A 核心推荐 | B384: 通用软件开发 | C384: 通用软件开发；售后／技术支持 | D384: 烽火通信 | E384: 软件研发；技术支持 | F384: 央国企 | G384: 通信/电子/半导体 | H384: 南京, 苏州, 武汉, 珠海, 成都, 西安, 海外 | I384: 2027届 | J384: 本科、硕士、博士 | K384: 46263 | L384: 具备软件工程基础、后端开发、联调和部署验证经验；具备操作指导、问题闭环、日志核验和研发升级经验 | M384: 通用软件开发简历；售后／技术支持简历 | N384: 与现有简历方向直接匹配，投递前仍需核对具体JD与专业限制 | O384: https://mp.weixin.qq.com/s/G4aveL1R6zlBvnZDaBMKxw | P384: https://app.mokahr.com/campus-recruitment/whfhtx/73922#/jobs | Q384: 未投递 | S384: 41
A385: A 核心推荐 | B385: 通用软件开发 | C385: 通用软件开发；项目经理／项目助理 | D385: 精进电动 | E385: 动力系统开发与应用工程师；测试工艺软件工程师；项目助理 | F385: 民企 | G385: 新能源 | H385: 北京, 石家庄, 菏泽 | I385: 2027届 | J385: 本科、硕士、博士 | K385: 46263 | L385: 具备软件工程基础、后端开发、联调和部署验证经验；具备22子系统、10家分包商和18个科室协同经验 | M385: 通用软件开发简历；项目经理／项目助理简历 | N385: 优先项目助理、交付、PMO及培养岗；避免要求独立负责大型项目 | O385: https://mp.weixin.qq.com/s/LdSswLoPi83S-zUEA-D0Wg | P385: https://wecruit.hotjob.cn/SU66d7f4aa6202cc2d4991438b/pb/school.html | Q385: 未投递 | S385: 26
A386: A 核心推荐 | B386: 商务拓展／BD | C386: 商务拓展／BD；数字化／IT项目；营销管培／市场销售；项目经理／项目助理 | D386: 象屿集团 | E386: 商务专员；数字化运营岗；业务管培生；营销管培生；项目专员；国内销售业务管培生 | F386: 央国企 | G386: 交通/物流/仓储, 贸易/批发/零售, 其他 | H386: 天津, 大连, 哈尔滨, 佳木斯, 黑河, 绥化, 上海, 苏州, 南通, 镇江, 杭州, 厦门, 青岛, 广州, 深圳, 成都, 西安, 银川, 全国多地, 海外 | I386: 2027届 | J386: 本科、硕士、博士 | K386: 46263 | L386: 具备主动拓客、需求识别、方案表达和复购跟进经验；具备政企信息化、多源数据和交付协同背景；另有1项 | M386: ToB销售／商务拓展简历；项目交付／通用软件开发简历；大客户销售／ToB销售简历；另有1项 | N386: 适合作为拓展方向，优先ToB、技术或行业客户场景；优先项目助理、交付、PMO及培养岗；另有1项 | O386: https://mp.weixin.qq.com/s/fIg1skur371GpgHhkN6dRA | P386: https://xiangyu.zhiye.com/campus/jobs | Q386: 未投递 | S386: 10
A387: A 核心推荐 | B387: 通用软件开发 | C387: 通用软件开发；售后／技术支持 | D387: 先进芯测 | E387: 助理软件工程师(平台)；助理软件工程师；助理技术支持工程师 | F387: 民企 | G387: 通信/电子/半导体, 机械/制造业 | H387: 苏州, 深圳, 东莞, 嘉兴 | I387: 2027届 | J387: 本科、硕士 | K387: 46262 | L387: 具备软件工程基础、后端开发、联调和部署验证经验；具备操作指导、问题闭环、日志核验和研发升级经验 | M387: 通用软件开发简历；售后／技术支持简历 | N387: 与现有简历方向直接匹配，投递前仍需核对具体JD与专业限制 | O387: https://mp.weixin.qq.com/s/iDO8Q-auD3BlAMgGEu1Idg | P387: https://v.wjx.cn/vm/PpgojG8.aspx | Q387: 未投递 | S387: 107
A388: A 核心推荐 | B388: 通用软件开发 | C388: 通用软件开发 | D388: 新时达 | E388: 软件工程师；软件开发工程师 | F388: 民企 | G388: 其他 | H388: 上海, 深圳 | I388: 2027届 | J388: 本科、硕士、博士 | K388: 46262 | L388: 具备软件工程基础、后端开发、联调和部署验证经验 | M388: 通用软件开发简历 | N388: 与现有简历方向直接匹配，投递前仍需核对具体JD与专业限制 | O388: https://mp.weixin.qq.com/s/B5EIPUJg8mGM2dJZXxdQyw | P388: https://maker.haier.net/client/campus/customizedptjobs/id/84.html | Q388: 未投递 | S388: 144
A389: A 核心推荐 | B389: 通用软件开发 | C389: 软件测试／测试开发；通用软件开发 | D389: 汇顶科技 | E389: 测试开发工程师；系统软件工程师 | F389: 民企 | G389: 通信/电子/半导体 | H389: 深圳, 成都, 武汉, 上海 | I389: 2027届 | J389: 本科、硕士、博士 | K389: 46262 | L389: 具备接口联调、问题跟踪和部署验证经验，但测试专项较弱；具备软件工程基础、后端开发、联调和部署验证经验 | M389: 通用软件开发简历（需补测试表述）；通用软件开发简历 | N389: 可投，但需补充测试用例、接口测试或自动化测试证据 | O389: https://mp.weixin.qq.com/s/jgA4n4mfQZKZdtdmJMhCVw | P389: https://goodix.zhiye.com/Promotion/ed3cdb53-698e-495f-83b6-0ed70b7b081a | Q389: 未投递 | S389: 110
A390: A 核心推荐 | B390: 商务拓展／BD | C390: 商务拓展／BD | D390: 泰科电子 (TE Connectivity） | E390: 客户商务专员 | F390: 外企 | G390: 通信/电子/半导体 | H390: 上海, 苏州, 南通 | I390: 2027届 | J390: 本科、硕士、博士 | K390: 46262 | L390: 具备主动拓客、需求识别、方案表达和复购跟进经验 | M390: ToB销售／商务拓展简历 | N390: 与现有简历方向直接匹配，投递前仍需核对具体JD与专业限制 | O390: https://mp.weixin.qq.com/s/J9BWFddLhMjEXCYnPuTx8Q | P390: https://campus.51job.com/te/p2.html | Q390: 未投递 | S390: 93
A391: A 核心推荐 | B391: 通用软件开发 | C391: 通用软件开发 | D391: 玖锦科技 | E391: FPGA工程师软件工程师 | F391: 民企 | G391: 通信/电子/半导体 | H391: 成都 | I391: 2027届 | J391: 本科、硕士、博士 | K391: 46262 | L391: 具备软件工程基础、后端开发、联调和部署验证经验 | M391: 通用软件开发简历 | N391: 与现有简历方向直接匹配，投递前仍需核对具体JD与专业限制 | O391: https://mp.weixin.qq.com/s/iaMFAGb2xO2HhY3T_1wHGQ?scene=1&click_id=503656341 | P391: https://mh.hire66.com/position?secret_key=UHaVro87cc | Q391: 未投递 | S391: 149
A392: A 核心推荐 | B392: 通用软件开发 | C392: 通用软件开发 | D392: 纽达投资 | E392: 系统开发工程师 | F392: 民企 | G392: 金融业 | H392: 深圳 | I392: 2027届, 2028届 | J392: 本科、硕士、博士 | K392: 46262 | L392: 具备软件工程基础、后端开发、联调和部署验证经验 | M392: 通用软件开发简历 | N392: 与现有简历方向直接匹配，投递前仍需核对具体JD与专业限制 | O392: https://mp.weixin.qq.com/s/sZBBntD5VZdmRcL0UCRFvg?scene=1 | P392: https://mp.weixin.qq.com/s/sZBBntD5VZdmRcL0UCRFvg?scene=1 | Q392: 未投递 | S392: 119
A393: A 核心推荐 | B393: 通用软件开发 | C393: 通用软件开发 | D393: 芯源微 | E393: 机械工程师 电气工程师软件工程师工艺工程师流体仿真工程师应用支持工程师 客服工程师调试工程师 财务管理 | F393: 民企 | G393: 机械/制造业 | H393: 上海, 沈阳, 北京, 武汉, 合肥 | I393: 2027届 | J393: 本科、硕士、博士 | K393: 46262 | L393: 具备软件工程基础、后端开发、联调和部署验证经验 | M393: 通用软件开发简历 | N393: 与现有简历方向直接匹配，投递前仍需核对具体JD与专业限制 | O393: https://mp.weixin.qq.com/s/jdMRIfPEijevlTCgskOq2g | P393: https://app.mokahr.com/campus-recruitment/688037/144533#/ | Q393: 未投递 | S393: 87
... A495: A 核心推荐 | B495: 通用软件开发 | C495: 通用软件开发；后端开发延伸；软件测试／测试开发 | D495: 芯动科技 | E495: GPU软件工程师；数字IC后端工程师；系统测试开发工程师 | F495: 民企 | G495: 通信/电子/半导体 | H495: 上海, 北京, 大连, 成都, 武汉, 珠海, 苏州, 西安 | I495: 2027届 | J495: 本科,硕士,博士 | K495: 46218 | L495: 具备软件工程基础、后端开发、联调和部署验证经验；具备Java后端基础，可尝试未限定语言的初级后端岗位；另有1项 | M495: 通用软件开发简历；Java后端／通用软件开发简历；通用软件开发简历（需补测试表述） | N495: 投递前确认技术栈以Java为主；明确要求其他语言的不建议投；另有1项 | O495: https://mp.weixin.qq.com/s/3UkbHbf-UCB_GNvaC6vq5w | P495: https://innosilicon.zhiye.com/campus/jobs | Q495: 未投递 | S495: 1914
A496: A 核心推荐 | B496: 通用软件开发 | C496: 通用软件开发 | D496: 宝时得 | E496: 软件研发岗 | G496: 机械/制造业 | H496: 苏州 | I496: 2027届 | J496: 本科, 硕士, 博士 | K496: 46210 | L496: 具备软件工程基础、后端开发、联调和部署验证经验 | M496: 通用软件开发简历 | N496: 与现有简历方向直接匹配，投递前仍需核对具体JD与专业限制 | O496: https://mp.weixin.qq.com/s/963ZfBd_oorBehgAkGSoAw | P496: https://wecruit.hotjob.cn/SU64ae431b2f9d24760adab44f/mc/position/intern | Q496: 未投递 | S496: 2001
A497: A 核心推荐 | B497: 通用软件开发 | C497: 通用软件开发 | D497: 恩智浦 | E497: 软件研发类 | F497: 外企 | G497: 通信/电子/半导体 | H497: 上海, 北京, 天津, 苏州, 重庆 | I497: 2025, 2026, 2027届 | J497: 本科,硕士,博士 | K497: 46207 | L497: 具备软件工程基础、后端开发、联调和部署验证经验 | M497: 通用软件开发简历 | N497: 与现有简历方向直接匹配，投递前仍需核对具体JD与专业限制 | O497: https://mp.weixin.qq.com/s/7ljyJtrGLgtemgXQSVjYvw | P497: https://campus.51job.com/nxp/graduates.html | Q497: 未投递 | S497: 2051
A498: A 核心推荐 | B498: 通用软件开发 | C498: 通用软件开发 | D498: 埃特曼半导体 | E498: 软件开发工程师 | F498: 民企 | G498: 通信/电子/半导体 | H498: 厦门 | I498: 2025, 2026, 2027届 | J498: 本科,硕士,博士 | K498: 46206 | L498: 具备软件工程基础、后端开发、联调和部署验证经验 | M498: 通用软件开发简历 | N498: 与现有简历方向直接匹配，投递前仍需核对具体JD与专业限制 | O498: https://scc.pku.edu.cn/frontpage/pku/html/recruitmentinfoForm.html?positionDetailId=204a5f57e6294224a8e39728a218c394& | P498: 邮箱投递：zhaopin@atoman.cc | Q498: 未投递 | S498: 2065
A499: A 核心推荐 | B499: 项目经理／项目助理 | C499: 项目经理／项目助理 | D499: 巨一科技 | E499: 项目管理类 | F499: 民企 | G499: 其他 | H499: 上海, 苏州, 合肥, 海外 | I499: 2027届 | J499: 本科、硕士、博士 | K499: 46263 | L499: 具备22子系统、10家分包商和18个科室协同经验 | M499: 项目经理／项目助理简历 | N499: 优先项目助理、交付、PMO及培养岗；避免要求独立负责大型项目 | O499: https://mp.weixin.qq.com/s/KtKIi3o71Dga1ixLkoRKMw | P499: https://app.mokahr.com/campus-recruitment/ahjy/168235?locale=zh-CN | Q499: 未投递 | S499: 13
A500: A 核心推荐 | B500: 售后／技术支持 | C500: 售后／技术支持 | D500: 海康集团 | E500: 算法类半导体类软件研发类硬件研发类营销/技术支持类管理类 | F500: 央国企 | G500: 通信/电子/半导体 | H500: 杭州 | I500: 2027届 | J500: 本科、硕士、博士 | K500: 46263 | L500: 具备操作指导、问题闭环、日志核验和研发升级经验 | M500: 售后／技术支持简历 | N500: 与现有简历方向直接匹配，投递前仍需核对具体JD与专业限制 | O500: https://mp.weixin.qq.com/s/qtA7eWQpz6XNnKYuEiNfBg | P500: https://wecruit.hotjob.cn/SU630076febef57c3179e31260/pb/school.html | Q500: 未投递 | S500: 42
A501: A 核心推荐 | B501: 售后／技术支持 | C501: 售后／技术支持 | D501: 珞珈伊云 | E501: 光学工程师C++工程师 市场技术支持结构工程师 FPGA工程师 硬件工程师产品导入工程师 生产工程师 工艺工程师电机生产工程师电路设计工程师嵌入式工程师 | F501: 民企 | G501: 通信/电子/半导体 | H501: 武汉 | I501: 2027届 | J501: 本科、硕士、博士 | K501: 46263 | L501: 具备操作指导、问题闭环、日志核验和研发升级经验 | M501: 售后／技术支持简历 | N501: 与现有简历方向直接匹配，投递前仍需核对具体JD与专业限制 | O501: https://mp.weixin.qq.com/s/iOZXwkNxCLJJVZZQFLHIhQ?scene=1&click_id=1011841635 | P501: https://mp.weixin.qq.com/s/iOZXwkNxCLJJVZZQFLHIhQ?scene=1&click_id=1011841635 | Q501: 未投递 | S501: 67
A502: A 核心推荐 | B502: 售后／技术支持 | C502: 售后／技术支持 | D502: 远东通信 | E502: 协议栈开发工程师嵌入式开发工程师射频开发工程师算法开发工程师音视频开发工程师 鸿蒙APP开发工程师 硬件开发工程师项目工程师工艺技术支持 | F502: 央国企 | G502: 通信/电子/半导体 | H502: 石家庄 | I502: 2026届, 2027届 | J502: 本科、硕士、博士 | K502: 46263 | L502: 具备操作指导、问题闭环、日志核验和研发升级经验 | M502: 售后／技术支持简历 | N502: 与现有简历方向直接匹配，投递前仍需核对具体JD与专业限制 | O502: https://mp.weixin.qq.com/s/FIHY1Eh4IIr4GeWngWIE6A?scene=1&click_id=2056000631 | P502: https://mp.weixin.qq.com/s/FIHY1Eh4IIr4GeWngWIE6A?scene=1&click_id=2056000631 | Q502: 未投递 | S502: 47
A503: A 核心推荐 | B503: 项目经理／项目助理 | C503: 项目经理／项目助理 | D503: 中国国家地理科考旅行部 | E503: 游轮项目助理（线上/线下） | F503: 事业单位 | G503: 文化/传媒/广告/体育 | H503: 北京 | I503: 2027届, 2028届 | J503: 本科、硕士、博士 | K503: 46262 | L503: 具备22子系统、10家分包商和18个科室协同经验 | M503: 项目经理／项目助理简历 | N503: 优先项目助理、交付、PMO及培养岗；避免要求独立负责大型项目 | O503: https://mp.weixin.qq.com/s/bSV9djAKVz9jucdnvKsWwQ | P503: https://mp.weixin.qq.com/s/bSV9djAKVz9jucdnvKsWwQ | Q503: 未投递 | S503: 123
A504: A 核心推荐 | B504: 售后／技术支持 | C504: 售后／技术支持 | D504: 云迹科技 | E504: 技术支持类 | F504: 民企 | G504: IT/互联网/游戏 | H504: 全国多地, 北京 | I504: 2027届 | J504: 本科、硕士、博士 | K504: 46262 | L504: 具备操作指导、问题闭环、日志核验和研发升级经验 | M504: 售后／技术支持简历 | N504: 与现有简历方向直接匹配，投递前仍需核对具体JD与专业限制 | O504: https://mp.weixin.qq.com/s/RZlLvJkYL1o3bmKvD5-Quw | P504: https://mp.weixin.qq.com/s/RZlLvJkYL1o3bmKvD5-Quw | Q504: 未投递 | S504: 102
A505: A 核心推荐 | B505: 售后／技术支持 | C505: 售后／技术支持 | D505: 惟甲科技 | E505: 应用/技术支持工程师 | F505: 民企 | G505: 通信/电子/半导体 | H505: 上海 | I505: 2027届 | J505: 本科、硕士、博士 | K505: 46262 | L505: 具备操作指导、问题闭环、日志核验和研发升级经验 | M505: 售后／技术支持简历 | N505: 与现有简历方向直接匹配，投递前仍需核对具体JD与专业限制 | O505: https://mp.weixin.qq.com/s/v7FYDoBLtfEwQYgjucYUJQ?scene=1&click_id=1471831125 | P505: https://mp.weixin.qq.com/s/v7FYDoBLtfEwQYgjucYUJQ?scene=1&click_id=1471831125 | Q505: 未投递 | S505: 153
A506: A 核心推荐 | B506: 项目经理／项目助理 | C506: 项目经理／项目助理 | D506: 澳鹏数据 | E506: 项目助理岗位 | F506: 外企 | G506: IT/互联网/游戏 | H506: 成都, 重庆, 大连, 无锡 | I506: 2027届 | J506: 本科、硕士、博士 | K506: 46262 | L506: 具备22子系统、10家分包商和18个科室协同经验 | M506: 项目经理／项目助理简历 | N506: 优先项目助理、交付、PMO及培养岗；避免要求独立负责大型项目 | O506: https://mp.weixin.qq.com/s/nBRD3qdoQJD__KBX9pLzZg | P506: https://oriendata.feishu.cn/share/base/form/shrcnNgBcRhgtxDmWTetXVmumzc | Q506: 未投递 | S506: 112
A507: A 核心推荐 | B507: 售后／技术支持 | C507: 售后／技术支持 | D507: 北方集成电路技术创新中心 | E507: 技术支持类 | F507: 民企 | G507: 通信/电子/半导体 | H507: 北京 | I507: 2027届 | J507: 本科、硕士、博士 | K507: 46261 | L507: 具备操作指导、问题闭环、日志核验和研发升级经验 | M507: 售后／技术支持简历 | N507: 与现有简历方向直接匹配，投递前仍需核对具体JD与专业限制 | O507: https://mp.weixin.qq.com/s/WuYeKyif97boMJFWnCp2tQ | P507: https://wecruit.hotjob.cn/SU63eed9fd2f9d246c468eb43d/pb/school.html | Q507: 未投递 | S507: 262
A508: A 核心推荐 | B508: 项目经理／项目助理 | C508: 项目经理／项目助理 | D508: 欧摩威 | E508: BenchTestIntern&PMOChina | F508: 外企 | G508: 通信/电子/半导体, 机械/制造业 | H508: 上海, 重庆 | I508: 2027届, 2028届 | J508: 本科、硕士、博士 | K508: 46261 | L508: 具备22子系统、10家分包商和18个科室协同经验 | M508: 项目经理／项目助理简历 | N508: 优先项目助理、交付、PMO及培养岗；避免要求独立负责大型项目 | O508: https://mp.weixin.qq.com/s/Jp51OqR2kOVa-PStG4Uqdw | P508: https://mp.weixin.qq.com/s/Jp51OqR2kOVa-PStG4Uqdw | Q508: 未投递 | S508: 219
... A544: A 核心推荐 | B544: 售后／技术支持 | C544: 售后／技术支持 | D544: 麦捷科技 | E544: 海外技术支持工程师 | F544: 民企 | G544: 通信/电子/半导体 | H544: 深圳, 惠州, 成都 | I544: 2027届 | J544: 本科、硕士、博士 | K544: 46238 | L544: 具备操作指导、问题闭环、日志核验和研发升级经验 | M544: 售后／技术支持简历 | N544: 与现有简历方向直接匹配，投递前仍需核对具体JD与专业限制 | O544: https://mp.weixin.qq.com/s/sELt3eLbPaIuNbZIuq3urA | P544: https://mp.weixin.qq.com/s/sELt3eLbPaIuNbZIuq3urA | Q544: 未投递 | S544: 1419
A545: A 核心推荐 | B545: 项目经理／项目助理 | C545: 项目经理／项目助理 | D545: BARTV波士顿中文广播电视台 | E545: 国际演艺业务项目经理（全职/兼职） | F545: 民企 | G545: 文化/传媒/广告/体育 | I545: 2027届, 2028届 | J545: 本科、硕士、博士 | K545: 46237 | L545: 具备22子系统、10家分包商和18个科室协同经验 | M545: 项目经理／项目助理简历 | N545: 优先项目助理、交付、PMO及培养岗；避免要求独立负责大型项目 | O545: https://mp.weixin.qq.com/s/nnim6beRv5socTZUFLjTyw | P545: https://mp.weixin.qq.com/s/nnim6beRv5socTZUFLjTyw | Q545: 未投递 | S545: 1497
A546: A 核心推荐 | B546: 售后／技术支持 | C546: 售后／技术支持 | D546: 岚图汽车 | E546: 产品领域研发领域营销领域智能制造服务支持 | F546: 央国企 | G546: 汽车制造/维修/零配件 | H546: 武汉, 北京, 上海, 宁波, 乌鲁木齐, 深圳, 石家庄, 厦门, 济南, 广州, 郑州 | I546: 2027届 | J546: 本科、硕士、博士 | K546: 46236 | L546: 具备操作指导、问题闭环、日志核验和研发升级经验 | M546: 售后／技术支持简历 | N546: 与现有简历方向直接匹配，投递前仍需核对具体JD与专业限制 | O546: https://mp.weixin.qq.com/s/5x6laCPG-kZgeFLc0v031w | P546: https://app.mokahr.com/campus-recruitment/voyah/146293#/jobs?project=100128215 | Q546: 未投递 | S546: 1508
A547: A 核心推荐 | B547: 售后／技术支持 | C547: 售后／技术支持 | D547: 浪潮集团 | E547: 核心研发类产品研发类技术支持类市场类职能管理类 | F547: 民企 | G547: IT/互联网/游戏 | H547: 济南, 北京, 天津, 青岛, 成都, 重庆, 苏州 | I547: 2027届 | J547: 本科、硕士、博士 | K547: 46236 | L547: 具备操作指导、问题闭环、日志核验和研发升级经验 | M547: 售后／技术支持简历 | N547: 与现有简历方向直接匹配，投递前仍需核对具体JD与专业限制 | O547: https://mp.weixin.qq.com/s/-BSsdPVR7ZEKz0MJzxyxoQ | P547: https://inspur.hcmcloud.cn/recruit#/portal_job_list?job_class=_HB5_Y2FtcHVz&filter_dict=_HB5_eyJf!m9iX2NsYXNzIjoiY2FtcHVzIiwic2VsZWN0X2RlcGFydCI6bnVsbH0%253D | Q547: 未投递 | S547: 1506
A548: A 核心推荐 | B548: 售后／技术支持 | C548: 售后／技术支持 | D548: 晋华集成电路 | E548: 研发工艺类IC设计类工程技术类生产营运类技术支持类 | F548: 央国企 | G548: 通信/电子/半导体 | H548: 泉州, 上海, 深圳 | I548: 2027届 | J548: 本科、硕士、博士 | K548: 46235 | L548: 具备操作指导、问题闭环、日志核验和研发升级经验 | M548: 售后／技术支持简历 | N548: 与现有简历方向直接匹配，投递前仍需核对具体JD与专业限制 | O548: https://mp.weixin.qq.com/s/edduPfJSYj5lnrRvmKzgcA | P548: https://www.jhicc.com/Recruiting/Campus/Index | Q548: 未投递 | S548: 1514
A549: A 核心推荐 | B549: 项目经理／项目助理 | C549: 项目经理／项目助理 | D549: 红树林基金会 | E549: 重建海上森林高级项目专员 | F549: 央国企 | G549: 农林牧渔 | H549: 深圳 | I549: 2027届, 2028届 | J549: 本科、硕士、博士 | K549: 46233 | L549: 具备22子系统、10家分包商和18个科室协同经验 | M549: 项目经理／项目助理简历 | N549: 优先项目助理、交付、PMO及培养岗；避免要求独立负责大型项目 | O549: https://mp.weixin.qq.com/s/GSiujExORecTQqTzwLjn-A?scene=1 | P549: https://mp.weixin.qq.com/s/GSiujExORecTQqTzwLjn-A?scene=1 | Q549: 未投递 | S549: 1602
A550: A 核心推荐 | B550: 项目经理／项目助理 | C550: 项目经理／项目助理 | D550: 维信诺 | E550: 产品开发类技术研发类数智化(AI)类工艺技术类市场营销类质量管理类智能制造类供应链管理类生产计划类项目管理类职能类厂务环安类 | F550: 民企 | G550: 通信/电子/半导体 | H550: 合肥, 苏州, 廊坊, 广州, 北京 | I550: 2027届 | J550: 本科、硕士、博士 | K550: 46233 | L550: 具备22子系统、10家分包商和18个科室协同经验 | M550: 项目经理／项目助理简历 | N550: 优先项目助理、交付、PMO及培养岗；避免要求独立负责大型项目 | O550: https://mp.weixin.qq.com/s/b4Koxr7taIrnzfkO4AVAAg | P550: https://app.mokahr.com/campus_apply/newvisionox/24735#/jobs?commitment=%E5%85%A8%E8%81%8C&zhineng=&page=1 | Q550: 未投递 | S550: 1615
A551: A 核心推荐 | B551: 售后／技术支持 | C551: 售后／技术支持 | D551: 奥比中光 | E551: 算法类软件类硬件类结构类产品类技术支持类销售类芯片类 | F551: 民企 | G551: 智能硬件 | H551: 深圳, 佛山, 上海, 西安, 杭州 | I551: 2027届 | J551: 本科、硕士、博士 | K551: 46232 | L551: 具备操作指导、问题闭环、日志核验和研发升级经验 | M551: 售后／技术支持简历 | N551: 与现有简历方向直接匹配，投递前仍需核对具体JD与专业限制 | O551: https://mp.weixin.qq.com/s/SEWDaGrFu0PQQpDz6_8D6w | P551: https://job.orbbec.com.cn/campus | Q551: 未投递 | S551: 1640
A552: A 核心推荐 | B552: 售后／技术支持 | C552: 售后／技术支持；后端开发延伸 | D552: 杭州龙旗科技 | E552: 策略技术支持；后端开发工程师 | F552: 民企 | G552: 金融业 | H552: 杭州 | I552: 2027届 | J552: 本科、硕士、博士 | K552: 46231 | L552: 具备操作指导、问题闭环、日志核验和研发升级经验；具备Java后端基础，可尝试未限定语言的初级后端岗位 | M552: 售后／技术支持简历；Java后端／通用软件开发简历 | N552: 投递前确认技术栈以Java为主；明确要求其他语言的不建议投 | O552: https://mp.weixin.qq.com/s/UFZiCzvSNlOsSA0RpD0x_A | P552: https://mp.weixin.qq.com/s/UFZiCzvSNlOsSA0RpD0x_A | Q552: 未投递 | S552: 1651
A553: A 核心推荐 | B553: 项目经理／项目助理 | C553: 项目经理／项目助理 | D553: 红树林基金会 | E553: 重建海上森林高级项目专员（全职） | F553: 央国企 | G553: 农林牧渔 | H553: 深圳 | I553: 2026届, 2027届 | J553: 本科、硕士、博士 | K553: 46230 | L553: 具备22子系统、10家分包商和18个科室协同经验 | M553: 项目经理／项目助理简历 | N553: 优先项目助理、交付、PMO及培养岗；避免要求独立负责大型项目 | O553: https://mp.weixin.qq.com/s/TMhldMsmv7oaOt67SRMmJA?scene=1 | P553: https://mp.weixin.qq.com/s/TMhldMsmv7oaOt67SRMmJA?scene=1 | Q553: 未投递 | S553: 1681
A554: A 核心推荐 | B554: 项目经理／项目助理 | C554: 项目经理／项目助理 | D554: 凯创御聘 | E554: 项目助理（实习岗） | F554: 民企 | G554: IT/互联网/游戏 | H554: 广州 | I554: 2027届 | J554: 本科、硕士、博士 | K554: 46227 | L554: 具备22子系统、10家分包商和18个科室协同经验 | M554: 项目经理／项目助理简历 | N554: 优先项目助理、交付、PMO及培养岗；避免要求独立负责大型项目 | O554: https://mp.weixin.qq.com/s/wR4W4gt4hkiuxkBb3dMKDg?clicktag=bar_share&scene=1&clickpos=0&from_safari=0 | P554: https://mp.weixin.qq.com/s/wR4W4gt4hkiuxkBb3dMKDg?clicktag=bar_share&scene=1&clickpos=0&from_safari=0 | Q554: 未投递 | S554: 1756
A555: A 核心推荐 | B555: 项目经理／项目助理 | C555: 项目经理／项目助理 | D555: 极飞科技 | E555: 项目管理类 | F555: 民企 | G555: 智能硬件 | H555: 广州, 东莞 | I555: 2027届 | J555: 本科、硕士、博士 | K555: 46227 | L555: 具备22子系统、10家分包商和18个科室协同经验 | M555: 项目经理／项目助理简历 | N555: 优先项目助理、交付、PMO及培养岗；避免要求独立负责大型项目 | O555: https://mp.weixin.qq.com/s/Syy4Fh4sMEMW2rVUUQRW6A | P555: https://zhaopin.xa.com/campus/jobs | Q555: 未投递 | S555: 1734
A556: A 核心推荐 | B556: 项目经理／项目助理 | C556: 项目经理／项目助理 | D556: 网易游戏（互娱） | E556: 项目管理类 | F556: 民企 | G556: IT/互联网/游戏 | H556: 上海, 杭州, 广州 | I556: 2027届 | J556: 本科、硕士、博士 | K556: 46224 | L556: 具备22子系统、10家分包商和18个科室协同经验 | M556: 项目经理／项目助理简历 | N556: 优先项目助理、交付、PMO及培养岗；避免要求独立负责大型项目 | O556: https://mp.weixin.qq.com/s/_JEgNaWh1kxlg1O81fjF9w | P556: https://campus.game.163.com/app/job/position?id=102 | Q556: 未投递 | S556: 1828
A557: A 核心推荐 | B557: 项目经理／项目助理 | C557: 数据平台／数据开发；项目经理／项目助理 | D557: 京企直聘 | E557: 数据工程师；项目助理 | F557: 央国企 | G557: 人力资源服务 | H557: 北京 | I557: 2024, 2025, 2026, 2027届 | J557: 本科,硕士,博士 | K557: 46222 | L557: 具备多数据源接入、SQL、聚合接口和库表设计经验；具备22子系统、10家分包商和18个科室协同经验 | M557: Java后端／通用软件开发简历；项目经理／项目助理简历 | N557: 适合数据接口/数据平台；不投算法型数据科学岗位；另有2项 | O557: https://mp.weixin.qq.com/s/ARkkMfaUyqfARatzGthh_w | P557: https://jqzp.fesco.com.cn/page?id=55 | Q557: 未投递 | S557: 1865
... A666: C 可尝试 | B666: 软件测试／测试开发 | C666: 软件测试／测试开发 | D666: 经纬恒润 | E666: 测试开发工程师-campus-2027 | F666: 民企 | G666: 汽车制造/维修/零配件 | H666: 北京, 天津, 南昌, 上海 | I666: 2027届 | J666: 本科、硕士、博士 | K666: 46228 | L666: 具备接口联调、问题跟踪和部署验证经验，但测试专项较弱 | M666: 通用软件开发简历（需补测试表述） | N666: 可投，但需补充测试用例、接口测试或自动化测试证据 | O666: 经纬恒润 - 校园招聘 | P666: https://app.mokahr.com/social-recruitment/jingweihengrun/168299?locale=zh-CN | Q666: 未投递 | S666: 1711
